[
  {
    "pattern": "batch_load",
    "method": "stale",
    "n_cases": 128,
    "qerror_gm": 4.202827477718372,
    "qerror_improvement_pct": 0.0,
    "selectivity_mae_mean": 0.3335475560656386,
    "quantile_mae_mean": 0.3652524969684063,
    "feedback_residual_mean": 0.26858125223880963,
    "beats_stale_frac": 0.0,
    "hybrid_isomer_frac": 0.6171875,
    "hybrid_oasis_projected_frac": 0.375,
    "hybrid_oasis_frac": 0.0078125,
    "hybrid_stale_frac": 0.0
  },
  {
    "pattern": "batch_load",
    "method": "isomer",
    "n_cases": 128,
    "qerror_gm": 1.460996297880612,
    "qerror_improvement_pct": 65.23777610129844,
    "selectivity_mae_mean": 0.04674036056139713,
    "quantile_mae_mean": 0.05226672057624971,
    "feedback_residual_mean": 0.08612539825381926,
    "beats_stale_frac": 1.0,
    "hybrid_isomer_frac": 0.6171875,
    "hybrid_oasis_projected_frac": 0.375,
    "hybrid_oasis_frac": 0.0078125,
    "hybrid_stale_frac": 0.0
  },
  {
    "pattern": "batch_load",
    "method": "oasis",
    "n_cases": 128,
    "qerror_gm": 1.9871492403187898,
    "qerror_improvement_pct": 52.71875300963883,
    "selectivity_mae_mean": 0.12722336636689321,
    "quantile_mae_mean": 0.13801768593751776,
    "feedback_residual_mean": 0.1732540564494789,
    "beats_stale_frac": 1.0,
    "hybrid_isomer_frac": 0.6171875,
    "hybrid_oasis_projected_frac": 0.375,
    "hybrid_oasis_frac": 0.0078125,
    "hybrid_stale_frac": 0.0
  },
  {
    "pattern": "batch_load",
    "method": "oasis_projected",
    "n_cases": 128,
    "qerror_gm": 1.251366469696416,
    "qerror_improvement_pct": 70.22560463567358,
    "selectivity_mae_mean": 0.028510456408902998,
    "quantile_mae_mean": 0.03193096731482027,
    "feedback_residual_mean": 0.0873231312596076,
    "beats_stale_frac": 1.0,
    "hybrid_isomer_frac": 0.6171875,
    "hybrid_oasis_projected_frac": 0.375,
    "hybrid_oasis_frac": 0.0078125,
    "hybrid_stale_frac": 0.0
  },
  {
    "pattern": "batch_load",
    "method": "oasis_soft_projection",
    "n_cases": 128,
    "qerror_gm": 1.4221657585818144,
    "qerror_improvement_pct": 66.16169076362185,
    "selectivity_mae_mean": 0.043679496285626396,
    "quantile_mae_mean": 0.048463971602198785,
    "feedback_residual_mean": 0.08396229258826207,
    "beats_stale_frac": 1.0,
    "hybrid_isomer_frac": 0.6171875,
    "hybrid_oasis_projected_frac": 0.375,
    "hybrid_oasis_frac": 0.0078125,
    "hybrid_stale_frac": 0.0
  },
  {
    "pattern": "batch_load",
    "method": "hybrid",
    "n_cases": 128,
    "qerror_gm": 1.3903974482197463,
    "qerror_improvement_pct": 66.91757024072365,
    "selectivity_mae_mean": 0.04006161738758745,
    "quantile_mae_mean": 0.04482507242008724,
    "feedback_residual_mean": 0.08463163896840646,
    "beats_stale_frac": 1.0,
    "hybrid_isomer_frac": 0.6171875,
    "hybrid_oasis_projected_frac": 0.375,
    "hybrid_oasis_frac": 0.0078125,
    "hybrid_stale_frac": 0.0
  },
  {
    "pattern": "batch_load",
    "method": "aggressive_hybrid",
    "n_cases": 128,
    "qerror_gm": 1.390491350028032,
    "qerror_improvement_pct": 66.91533598750283,
    "selectivity_mae_mean": 0.04035541978733119,
    "quantile_mae_mean": 0.045241248201125205,
    "feedback_residual_mean": 0.08293198966462278,
    "beats_stale_frac": 1.0,
    "hybrid_isomer_frac": 0.6171875,
    "hybrid_oasis_projected_frac": 0.375,
    "hybrid_oasis_frac": 0.0078125,
    "hybrid_stale_frac": 0.0
  },
  {
    "pattern": "batch_load",
    "method": "fresh",
    "n_cases": 128,
    "qerror_gm": 1.0,
    "qerror_improvement_pct": 76.20649419226507,
    "selectivity_mae_mean": 0.0,
    "quantile_mae_mean": 0.0,
    "feedback_residual_mean": 0.09602466110786623,
    "beats_stale_frac": 1.0,
    "hybrid_isomer_frac": 0.6171875,
    "hybrid_oasis_projected_frac": 0.375,
    "hybrid_oasis_frac": 0.0078125,
    "hybrid_stale_frac": 0.0
  },
  {
    "pattern": "range_shift",
    "method": "stale",
    "n_cases": 128,
    "qerror_gm": 1.9941217964572877,
    "qerror_improvement_pct": 0.0,
    "selectivity_mae_mean": 0.22579253887117917,
    "quantile_mae_mean": 0.25270480403054946,
    "feedback_residual_mean": 0.1715393878480322,
    "beats_stale_frac": 0.0,
    "hybrid_isomer_frac": 0.75,
    "hybrid_oasis_projected_frac": 0.21875,
    "hybrid_oasis_frac": 0.03125,
    "hybrid_stale_frac": 0.0
  },
  {
    "pattern": "range_shift",
    "method": "isomer",
    "n_cases": 128,
    "qerror_gm": 1.2104394195062438,
    "qerror_improvement_pct": 39.29962444336733,
    "selectivity_mae_mean": 0.058347279215219434,
    "quantile_mae_mean": 0.06568013317460816,
    "feedback_residual_mean": 0.10852093206057403,
    "beats_stale_frac": 1.0,
    "hybrid_isomer_frac": 0.75,
    "hybrid_oasis_projected_frac": 0.21875,
    "hybrid_oasis_frac": 0.03125,
    "hybrid_stale_frac": 0.0
  },
  {
    "pattern": "range_shift",
    "method": "oasis",
    "n_cases": 128,
    "qerror_gm": 1.3814230655731818,
    "qerror_improvement_pct": 30.725241154909032,
    "selectivity_mae_mean": 0.10048339568910117,
    "quantile_mae_mean": 0.11388423972497201,
    "feedback_residual_mean": 0.142312430527268,
    "beats_stale_frac": 1.0,
    "hybrid_isomer_frac": 0.75,
    "hybrid_oasis_projected_frac": 0.21875,
    "hybrid_oasis_frac": 0.03125,
    "hybrid_stale_frac": 0.0
  },
  {
    "pattern": "range_shift",
    "method": "oasis_projected",
    "n_cases": 128,
    "qerror_gm": 1.211530004910528,
    "qerror_improvement_pct": 39.24493443364868,
    "selectivity_mae_mean": 0.04894825427185899,
    "quantile_mae_mean": 0.05663923243597117,
    "feedback_residual_mean": 0.11278817729085329,
    "beats_stale_frac": 1.0,
    "hybrid_isomer_frac": 0.75,
    "hybrid_oasis_projected_frac": 0.21875,
    "hybrid_oasis_frac": 0.03125,
    "hybrid_stale_frac": 0.0
  },
  {
    "pattern": "range_shift",
    "method": "oasis_soft_projection",
    "n_cases": 128,
    "qerror_gm": 1.2859927748554911,
    "qerror_improvement_pct": 35.51082099698438,
    "selectivity_mae_mean": 0.06580189489035422,
    "quantile_mae_mean": 0.07438282365022823,
    "feedback_residual_mean": 0.10511728784253406,
    "beats_stale_frac": 1.0,
    "hybrid_isomer_frac": 0.75,
    "hybrid_oasis_projected_frac": 0.21875,
    "hybrid_oasis_frac": 0.03125,
    "hybrid_stale_frac": 0.0
  },
  {
    "pattern": "range_shift",
    "method": "hybrid",
    "n_cases": 128,
    "qerror_gm": 1.2212459606180444,
    "qerror_improvement_pct": 38.75770463029477,
    "selectivity_mae_mean": 0.05920342664364253,
    "quantile_mae_mean": 0.06664988296749065,
    "feedback_residual_mean": 0.10805014750309805,
    "beats_stale_frac": 1.0,
    "hybrid_isomer_frac": 0.75,
    "hybrid_oasis_projected_frac": 0.21875,
    "hybrid_oasis_frac": 0.03125,
    "hybrid_stale_frac": 0.0
  },
  {
    "pattern": "range_shift",
    "method": "aggressive_hybrid",
    "n_cases": 128,
    "qerror_gm": 1.2286010997189325,
    "qerror_improvement_pct": 38.38886361396592,
    "selectivity_mae_mean": 0.06047427414745848,
    "quantile_mae_mean": 0.06796102381113397,
    "feedback_residual_mean": 0.10749027775186938,
    "beats_stale_frac": 1.0,
    "hybrid_isomer_frac": 0.75,
    "hybrid_oasis_projected_frac": 0.21875,
    "hybrid_oasis_frac": 0.03125,
    "hybrid_stale_frac": 0.0
  },
  {
    "pattern": "range_shift",
    "method": "fresh",
    "n_cases": 128,
    "qerror_gm": 1.0,
    "qerror_improvement_pct": 49.85261172228408,
    "selectivity_mae_mean": 0.0,
    "quantile_mae_mean": 0.0,
    "feedback_residual_mean": 0.12598971230952358,
    "beats_stale_frac": 1.0,
    "hybrid_isomer_frac": 0.75,
    "hybrid_oasis_projected_frac": 0.21875,
    "hybrid_oasis_frac": 0.03125,
    "hybrid_stale_frac": 0.0
  },
  {
    "pattern": "skew_evol",
    "method": "stale",
    "n_cases": 128,
    "qerror_gm": 1.540036462758163,
    "qerror_improvement_pct": 0.0,
    "selectivity_mae_mean": 0.17866423917608443,
    "quantile_mae_mean": 0.201151625532698,
    "feedback_residual_mean": 0.10919034581082979,
    "beats_stale_frac": 0.0,
    "hybrid_isomer_frac": 0.734375,
    "hybrid_oasis_projected_frac": 0.265625,
    "hybrid_oasis_frac": 0.0,
    "hybrid_stale_frac": 0.0
  },
  {
    "pattern": "skew_evol",
    "method": "isomer",
    "n_cases": 128,
    "qerror_gm": 1.181610141461452,
    "qerror_improvement_pct": 23.27388538936146,
    "selectivity_mae_mean": 0.04979782223407465,
    "quantile_mae_mean": 0.057264754771826354,
    "feedback_residual_mean": 0.03974498728325283,
    "beats_stale_frac": 0.9765625,
    "hybrid_isomer_frac": 0.734375,
    "hybrid_oasis_projected_frac": 0.265625,
    "hybrid_oasis_frac": 0.0,
    "hybrid_stale_frac": 0.0
  },
  {
    "pattern": "skew_evol",
    "method": "oasis",
    "n_cases": 128,
    "qerror_gm": 1.5206050947303522,
    "qerror_improvement_pct": 1.2617472701269568,
    "selectivity_mae_mean": 0.11271466107967006,
    "quantile_mae_mean": 0.12876723723211458,
    "feedback_residual_mean": 0.09336910316007327,
    "beats_stale_frac": 0.65625,
    "hybrid_isomer_frac": 0.734375,
    "hybrid_oasis_projected_frac": 0.265625,
    "hybrid_oasis_frac": 0.0,
    "hybrid_stale_frac": 0.0
  },
  {
    "pattern": "skew_evol",
    "method": "oasis_projected",
    "n_cases": 128,
    "qerror_gm": 1.1712111023173146,
    "qerror_improvement_pct": 23.94913168356367,
    "selectivity_mae_mean": 0.04589242886912385,
    "quantile_mae_mean": 0.05308517314367409,
    "feedback_residual_mean": 0.04439286506266355,
    "beats_stale_frac": 0.9609375,
    "hybrid_isomer_frac": 0.734375,
    "hybrid_oasis_projected_frac": 0.265625,
    "hybrid_oasis_frac": 0.0,
    "hybrid_stale_frac": 0.0
  },
  {
    "pattern": "skew_evol",
    "method": "oasis_soft_projection",
    "n_cases": 128,
    "qerror_gm": 1.16285607325858,
    "qerror_improvement_pct": 24.49165319268242,
    "selectivity_mae_mean": 0.053488406873599,
    "quantile_mae_mean": 0.06213551544865099,
    "feedback_residual_mean": 0.03858304016335295,
    "beats_stale_frac": 0.9921875,
    "hybrid_isomer_frac": 0.734375,
    "hybrid_oasis_projected_frac": 0.265625,
    "hybrid_oasis_frac": 0.0,
    "hybrid_stale_frac": 0.0
  },
  {
    "pattern": "skew_evol",
    "method": "hybrid",
    "n_cases": 128,
    "qerror_gm": 1.174080112874145,
    "qerror_improvement_pct": 23.762836707684205,
    "selectivity_mae_mean": 0.049589274628716776,
    "quantile_mae_mean": 0.05731282559838695,
    "feedback_residual_mean": 0.039337097303149826,
    "beats_stale_frac": 0.984375,
    "hybrid_isomer_frac": 0.734375,
    "hybrid_oasis_projected_frac": 0.265625,
    "hybrid_oasis_frac": 0.0,
    "hybrid_stale_frac": 0.0
  },
  {
    "pattern": "skew_evol",
    "method": "aggressive_hybrid",
    "n_cases": 128,
    "qerror_gm": 1.1732239336527726,
    "qerror_improvement_pct": 23.81843144469705,
    "selectivity_mae_mean": 0.05053174393468917,
    "quantile_mae_mean": 0.058312940063957514,
    "feedback_residual_mean": 0.03881395367984654,
    "beats_stale_frac": 0.984375,
    "hybrid_isomer_frac": 0.734375,
    "hybrid_oasis_projected_frac": 0.265625,
    "hybrid_oasis_frac": 0.0,
    "hybrid_stale_frac": 0.0
  },
  {
    "pattern": "skew_evol",
    "method": "fresh",
    "n_cases": 128,
    "qerror_gm": 1.0,
    "qerror_improvement_pct": 35.06647250357778,
    "selectivity_mae_mean": 0.0,
    "quantile_mae_mean": 0.0,
    "feedback_residual_mean": 0.054892603767530176,
    "beats_stale_frac": 1.0,
    "hybrid_isomer_frac": 0.734375,
    "hybrid_oasis_projected_frac": 0.265625,
    "hybrid_oasis_frac": 0.0,
    "hybrid_stale_frac": 0.0
  },
  {
    "pattern": "outlier",
    "method": "stale",
    "n_cases": 128,
    "qerror_gm": 1.257842409831603,
    "qerror_improvement_pct": 0.0,
    "selectivity_mae_mean": 0.06069583857161633,
    "quantile_mae_mean": 0.06776332332425172,
    "feedback_residual_mean": 0.052425972117799736,
    "beats_stale_frac": 0.0,
    "hybrid_isomer_frac": 0.625,
    "hybrid_oasis_projected_frac": 0.3671875,
    "hybrid_oasis_frac": 0.0,
    "hybrid_stale_frac": 0.0078125
  },
  {
    "pattern": "outlier",
    "method": "isomer",
    "n_cases": 128,
    "qerror_gm": 1.0761705134593094,
    "qerror_improvement_pct": 14.443136513151552,
    "selectivity_mae_mean": 0.01644198478514215,
    "quantile_mae_mean": 0.01868806303557558,
    "feedback_residual_mean": 0.01679986060186006,
    "beats_stale_frac": 0.9765625,
    "hybrid_isomer_frac": 0.625,
    "hybrid_oasis_projected_frac": 0.3671875,
    "hybrid_oasis_frac": 0.0,
    "hybrid_stale_frac": 0.0078125
  },
  {
    "pattern": "outlier",
    "method": "oasis",
    "n_cases": 128,
    "qerror_gm": 1.1390054364953115,
    "qerror_improvement_pct": 9.447683780371273,
    "selectivity_mae_mean": 0.03309537872857381,
    "quantile_mae_mean": 0.037335190330153,
    "feedback_residual_mean": 0.051130457224882846,
    "beats_stale_frac": 0.7578125,
    "hybrid_isomer_frac": 0.625,
    "hybrid_oasis_projected_frac": 0.3671875,
    "hybrid_oasis_frac": 0.0,
    "hybrid_stale_frac": 0.0078125
  },
  {
    "pattern": "outlier",
    "method": "oasis_projected",
    "n_cases": 128,
    "qerror_gm": 1.0640641454870947,
    "qerror_improvement_pct": 15.405607477525812,
    "selectivity_mae_mean": 0.012705176418745303,
    "quantile_mae_mean": 0.014903583536005082,
    "feedback_residual_mean": 0.01854425122553477,
    "beats_stale_frac": 0.9921875,
    "hybrid_isomer_frac": 0.625,
    "hybrid_oasis_projected_frac": 0.3671875,
    "hybrid_oasis_frac": 0.0,
    "hybrid_stale_frac": 0.0078125
  },
  {
    "pattern": "outlier",
    "method": "oasis_soft_projection",
    "n_cases": 128,
    "qerror_gm": 1.071881105962193,
    "qerror_improvement_pct": 14.784149621279344,
    "selectivity_mae_mean": 0.01393105816031904,
    "quantile_mae_mean": 0.015878253942396316,
    "feedback_residual_mean": 0.018246574187956013,
    "beats_stale_frac": 0.984375,
    "hybrid_isomer_frac": 0.625,
    "hybrid_oasis_projected_frac": 0.3671875,
    "hybrid_oasis_frac": 0.0,
    "hybrid_stale_frac": 0.0078125
  },
  {
    "pattern": "outlier",
    "method": "hybrid",
    "n_cases": 128,
    "qerror_gm": 1.0706270896907273,
    "qerror_improvement_pct": 14.88384543863008,
    "selectivity_mae_mean": 0.015070377694041156,
    "quantile_mae_mean": 0.017030927028397383,
    "feedback_residual_mean": 0.016254934424437737,
    "beats_stale_frac": 0.9921875,
    "hybrid_isomer_frac": 0.625,
    "hybrid_oasis_projected_frac": 0.3671875,
    "hybrid_oasis_frac": 0.0,
    "hybrid_stale_frac": 0.0078125
  },
  {
    "pattern": "outlier",
    "method": "aggressive_hybrid",
    "n_cases": 128,
    "qerror_gm": 1.0708875330150958,
    "qerror_improvement_pct": 14.86313987787519,
    "selectivity_mae_mean": 0.015187265480438665,
    "quantile_mae_mean": 0.017157592215109242,
    "feedback_residual_mean": 0.016062049459318946,
    "beats_stale_frac": 0.984375,
    "hybrid_isomer_frac": 0.625,
    "hybrid_oasis_projected_frac": 0.3671875,
    "hybrid_oasis_frac": 0.0,
    "hybrid_stale_frac": 0.0078125
  },
  {
    "pattern": "outlier",
    "method": "fresh",
    "n_cases": 128,
    "qerror_gm": 1.0,
    "qerror_improvement_pct": 20.498784888809908,
    "selectivity_mae_mean": 0.0,
    "quantile_mae_mean": 0.0,
    "feedback_residual_mean": 0.02324853228991316,
    "beats_stale_frac": 1.0,
    "hybrid_isomer_frac": 0.625,
    "hybrid_oasis_projected_frac": 0.3671875,
    "hybrid_oasis_frac": 0.0,
    "hybrid_stale_frac": 0.0078125
  },
  {
    "pattern": "multimodal",
    "method": "stale",
    "n_cases": 128,
    "qerror_gm": 1.2383540105707764,
    "qerror_improvement_pct": 0.0,
    "selectivity_mae_mean": 0.07310567519877008,
    "quantile_mae_mean": 0.0806007050214004,
    "feedback_residual_mean": 0.05496114939310764,
    "beats_stale_frac": 0.0,
    "hybrid_isomer_frac": 0.6953125,
    "hybrid_oasis_projected_frac": 0.296875,
    "hybrid_oasis_frac": 0.0078125,
    "hybrid_stale_frac": 0.0
  },
  {
    "pattern": "multimodal",
    "method": "isomer",
    "n_cases": 128,
    "qerror_gm": 1.0660610600625566,
    "qerror_improvement_pct": 13.913061130944884,
    "selectivity_mae_mean": 0.020351580107091677,
    "quantile_mae_mean": 0.023448257880159234,
    "feedback_residual_mean": 0.020717903846606114,
    "beats_stale_frac": 0.9921875,
    "hybrid_isomer_frac": 0.6953125,
    "hybrid_oasis_projected_frac": 0.296875,
    "hybrid_oasis_frac": 0.0078125,
    "hybrid_stale_frac": 0.0
  },
  {
    "pattern": "multimodal",
    "method": "oasis",
    "n_cases": 128,
    "qerror_gm": 1.1356730958570944,
    "qerror_improvement_pct": 8.291725454690845,
    "selectivity_mae_mean": 0.04134427541108883,
    "quantile_mae_mean": 0.0473638309294849,
    "feedback_residual_mean": 0.05495245809540071,
    "beats_stale_frac": 0.8046875,
    "hybrid_isomer_frac": 0.6953125,
    "hybrid_oasis_projected_frac": 0.296875,
    "hybrid_oasis_frac": 0.0078125,
    "hybrid_stale_frac": 0.0
  },
  {
    "pattern": "multimodal",
    "method": "oasis_projected",
    "n_cases": 128,
    "qerror_gm": 1.0630442442135255,
    "qerror_improvement_pct": 14.156676108833205,
    "selectivity_mae_mean": 0.019425882207562452,
    "quantile_mae_mean": 0.02249847400081952,
    "feedback_residual_mean": 0.022477967909232625,
    "beats_stale_frac": 0.9921875,
    "hybrid_isomer_frac": 0.6953125,
    "hybrid_oasis_projected_frac": 0.296875,
    "hybrid_oasis_frac": 0.0078125,
    "hybrid_stale_frac": 0.0
  },
  {
    "pattern": "multimodal",
    "method": "oasis_soft_projection",
    "n_cases": 128,
    "qerror_gm": 1.0645283837358261,
    "qerror_improvement_pct": 14.03682835046752,
    "selectivity_mae_mean": 0.021224688429928886,
    "quantile_mae_mean": 0.024757992831416477,
    "feedback_residual_mean": 0.021757351278652613,
    "beats_stale_frac": 0.9765625,
    "hybrid_isomer_frac": 0.6953125,
    "hybrid_oasis_projected_frac": 0.296875,
    "hybrid_oasis_frac": 0.0078125,
    "hybrid_stale_frac": 0.0
  },
  {
    "pattern": "multimodal",
    "method": "hybrid",
    "n_cases": 128,
    "qerror_gm": 1.0653760652093311,
    "qerror_improvement_pct": 13.968376077024782,
    "selectivity_mae_mean": 0.02030921930929989,
    "quantile_mae_mean": 0.023317321737508858,
    "feedback_residual_mean": 0.020406224095051585,
    "beats_stale_frac": 1.0,
    "hybrid_isomer_frac": 0.6953125,
    "hybrid_oasis_projected_frac": 0.296875,
    "hybrid_oasis_frac": 0.0078125,
    "hybrid_stale_frac": 0.0
  },
  {
    "pattern": "multimodal",
    "method": "aggressive_hybrid",
    "n_cases": 128,
    "qerror_gm": 1.0689416115071526,
    "qerror_improvement_pct": 13.680449824322775,
    "selectivity_mae_mean": 0.021178979868604366,
    "quantile_mae_mean": 0.024193227894436092,
    "feedback_residual_mean": 0.020152635398420885,
    "beats_stale_frac": 0.984375,
    "hybrid_isomer_frac": 0.6953125,
    "hybrid_oasis_projected_frac": 0.296875,
    "hybrid_oasis_frac": 0.0078125,
    "hybrid_stale_frac": 0.0
  },
  {
    "pattern": "multimodal",
    "method": "fresh",
    "n_cases": 128,
    "qerror_gm": 1.0,
    "qerror_improvement_pct": 19.2476471619707,
    "selectivity_mae_mean": 0.0,
    "quantile_mae_mean": 0.0,
    "feedback_residual_mean": 0.027804585263821104,
    "beats_stale_frac": 1.0,
    "hybrid_isomer_frac": 0.6953125,
    "hybrid_oasis_projected_frac": 0.296875,
    "hybrid_oasis_frac": 0.0078125,
    "hybrid_stale_frac": 0.0
  },
  {
    "pattern": "seasonal",
    "method": "stale",
    "n_cases": 128,
    "qerror_gm": 1.2115932686404,
    "qerror_improvement_pct": 0.0,
    "selectivity_mae_mean": 0.052153364848734715,
    "quantile_mae_mean": 0.05916806119040322,
    "feedback_residual_mean": 0.04178565561549942,
    "beats_stale_frac": 0.0,
    "hybrid_isomer_frac": 0.6796875,
    "hybrid_oasis_projected_frac": 0.3203125,
    "hybrid_oasis_frac": 0.0,
    "hybrid_stale_frac": 0.0
  },
  {
    "pattern": "seasonal",
    "method": "isomer",
    "n_cases": 128,
    "qerror_gm": 1.06577911700243,
    "qerror_improvement_pct": 12.034909355480051,
    "selectivity_mae_mean": 0.016288991604704907,
    "quantile_mae_mean": 0.018308751736327268,
    "feedback_residual_mean": 0.017271848596624936,
    "beats_stale_frac": 0.9921875,
    "hybrid_isomer_frac": 0.6796875,
    "hybrid_oasis_projected_frac": 0.3203125,
    "hybrid_oasis_frac": 0.0,
    "hybrid_stale_frac": 0.0
  },
  {
    "pattern": "seasonal",
    "method": "oasis",
    "n_cases": 128,
    "qerror_gm": 1.1272202191034797,
    "qerror_improvement_pct": 6.963809697589383,
    "selectivity_mae_mean": 0.03420819132947167,
    "quantile_mae_mean": 0.038546004025538594,
    "feedback_residual_mean": 0.05170814687240264,
    "beats_stale_frac": 0.8125,
    "hybrid_isomer_frac": 0.6796875,
    "hybrid_oasis_projected_frac": 0.3203125,
    "hybrid_oasis_frac": 0.0,
    "hybrid_stale_frac": 0.0
  },
  {
    "pattern": "seasonal",
    "method": "oasis_projected",
    "n_cases": 128,
    "qerror_gm": 1.0583862541206852,
    "qerror_improvement_pct": 12.645086307852917,
    "selectivity_mae_mean": 0.013732147405746124,
    "quantile_mae_mean": 0.015392281767702673,
    "feedback_residual_mean": 0.019300247383020386,
    "beats_stale_frac": 0.9921875,
    "hybrid_isomer_frac": 0.6796875,
    "hybrid_oasis_projected_frac": 0.3203125,
    "hybrid_oasis_frac": 0.0,
    "hybrid_stale_frac": 0.0
  },
  {
    "pattern": "seasonal",
    "method": "oasis_soft_projection",
    "n_cases": 128,
    "qerror_gm": 1.0640814268329128,
    "qerror_improvement_pct": 12.175029824407899,
    "selectivity_mae_mean": 0.014497129267908405,
    "quantile_mae_mean": 0.01674254034070691,
    "feedback_residual_mean": 0.019019551531388134,
    "beats_stale_frac": 0.9921875,
    "hybrid_isomer_frac": 0.6796875,
    "hybrid_oasis_projected_frac": 0.3203125,
    "hybrid_oasis_frac": 0.0,
    "hybrid_stale_frac": 0.0
  },
  {
    "pattern": "seasonal",
    "method": "hybrid",
    "n_cases": 128,
    "qerror_gm": 1.0628555081197175,
    "qerror_improvement_pct": 12.276212188566376,
    "selectivity_mae_mean": 0.015536199744408683,
    "quantile_mae_mean": 0.017400619934133277,
    "feedback_residual_mean": 0.016854481181112303,
    "beats_stale_frac": 0.9921875,
    "hybrid_isomer_frac": 0.6796875,
    "hybrid_oasis_projected_frac": 0.3203125,
    "hybrid_oasis_frac": 0.0,
    "hybrid_stale_frac": 0.0
  },
  {
    "pattern": "seasonal",
    "method": "aggressive_hybrid",
    "n_cases": 128,
    "qerror_gm": 1.0619819775969055,
    "qerror_improvement_pct": 12.34830985908185,
    "selectivity_mae_mean": 0.015367317789431774,
    "quantile_mae_mean": 0.017346314917911675,
    "feedback_residual_mean": 0.016661999187473863,
    "beats_stale_frac": 0.984375,
    "hybrid_isomer_frac": 0.6796875,
    "hybrid_oasis_projected_frac": 0.3203125,
    "hybrid_oasis_frac": 0.0,
    "hybrid_stale_frac": 0.0
  },
  {
    "pattern": "seasonal",
    "method": "fresh",
    "n_cases": 128,
    "qerror_gm": 1.0,
    "qerror_improvement_pct": 17.46405118921148,
    "selectivity_mae_mean": 0.0,
    "quantile_mae_mean": 0.0,
    "feedback_residual_mean": 0.025207103385234117,
    "beats_stale_frac": 1.0,
    "hybrid_isomer_frac": 0.6796875,
    "hybrid_oasis_projected_frac": 0.3203125,
    "hybrid_oasis_frac": 0.0,
    "hybrid_stale_frac": 0.0
  }
]