[
  {
    "family": "all",
    "method": "stale",
    "n": 84,
    "row_qerr_gm": 35.24602033631592,
    "qerr_improvement_pct": 0.0,
    "beats_stale_qerr_frac": 0.0,
    "fresh_plan_match_frac": 0.5,
    "fresh_root_match_frac": 0.5833333333333334,
    "fresh_scan_match_frac": 0.5,
    "fresh_join_match_frac": 0.6666666666666666,
    "stale_fresh_changed_queries": 42,
    "plan_recovery_frac": 0.0,
    "new_plan_deviation_frac": 0.0
  },
  {
    "family": "all",
    "method": "isomer",
    "n": 84,
    "row_qerr_gm": 1.9708898269695634,
    "qerr_improvement_pct": 94.40819188049198,
    "beats_stale_qerr_frac": 0.9761904761904762,
    "fresh_plan_match_frac": 0.9761904761904762,
    "fresh_root_match_frac": 0.9761904761904762,
    "fresh_scan_match_frac": 0.9761904761904762,
    "fresh_join_match_frac": 0.9761904761904762,
    "stale_fresh_changed_queries": 42,
    "plan_recovery_frac": 0.9523809523809523,
    "new_plan_deviation_frac": 0.0
  },
  {
    "family": "all",
    "method": "oasis",
    "n": 84,
    "row_qerr_gm": 2.949379287682551,
    "qerr_improvement_pct": 91.63202182958612,
    "beats_stale_qerr_frac": 0.9285714285714286,
    "fresh_plan_match_frac": 0.9166666666666666,
    "fresh_root_match_frac": 0.9285714285714286,
    "fresh_scan_match_frac": 0.9166666666666666,
    "fresh_join_match_frac": 0.9404761904761905,
    "stale_fresh_changed_queries": 42,
    "plan_recovery_frac": 0.9523809523809523,
    "new_plan_deviation_frac": 0.11904761904761904
  },
  {
    "family": "all",
    "method": "oasis_projected",
    "n": 84,
    "row_qerr_gm": 2.0263195360247215,
    "qerr_improvement_pct": 94.25092672395444,
    "beats_stale_qerr_frac": 0.9761904761904762,
    "fresh_plan_match_frac": 0.9761904761904762,
    "fresh_root_match_frac": 0.9761904761904762,
    "fresh_scan_match_frac": 0.9761904761904762,
    "fresh_join_match_frac": 0.9761904761904762,
    "stale_fresh_changed_queries": 42,
    "plan_recovery_frac": 0.9523809523809523,
    "new_plan_deviation_frac": 0.0
  },
  {
    "family": "all",
    "method": "hybrid",
    "n": 84,
    "row_qerr_gm": 2.0092464191905695,
    "qerr_improvement_pct": 94.29936656672602,
    "beats_stale_qerr_frac": 0.9761904761904762,
    "fresh_plan_match_frac": 0.9761904761904762,
    "fresh_root_match_frac": 0.9761904761904762,
    "fresh_scan_match_frac": 0.9761904761904762,
    "fresh_join_match_frac": 0.9761904761904762,
    "stale_fresh_changed_queries": 42,
    "plan_recovery_frac": 0.9523809523809523,
    "new_plan_deviation_frac": 0.0
  },
  {
    "family": "all",
    "method": "aggressive_hybrid",
    "n": 84,
    "row_qerr_gm": 2.020567674685662,
    "qerr_improvement_pct": 94.2672459034935,
    "beats_stale_qerr_frac": 0.9761904761904762,
    "fresh_plan_match_frac": 0.9761904761904762,
    "fresh_root_match_frac": 0.9761904761904762,
    "fresh_scan_match_frac": 0.9761904761904762,
    "fresh_join_match_frac": 0.9761904761904762,
    "stale_fresh_changed_queries": 42,
    "plan_recovery_frac": 0.9523809523809523,
    "new_plan_deviation_frac": 0.0
  },
  {
    "family": "all",
    "method": "fresh",
    "n": 84,
    "row_qerr_gm": 1.333680755464982,
    "qerr_improvement_pct": 96.21608129729525,
    "beats_stale_qerr_frac": 1.0,
    "fresh_plan_match_frac": 1.0,
    "fresh_root_match_frac": 1.0,
    "fresh_scan_match_frac": 1.0,
    "fresh_join_match_frac": 1.0,
    "stale_fresh_changed_queries": 42,
    "plan_recovery_frac": 1.0,
    "new_plan_deviation_frac": 0.0
  },
  {
    "family": "scan",
    "method": "stale",
    "n": 28,
    "row_qerr_gm": 36.042946579978334,
    "qerr_improvement_pct": 0.0,
    "beats_stale_qerr_frac": 0.0,
    "fresh_plan_match_frac": 0.75,
    "fresh_root_match_frac": 0.75,
    "fresh_scan_match_frac": 0.75,
    "fresh_join_match_frac": 1.0,
    "stale_fresh_changed_queries": 7,
    "plan_recovery_frac": 0.0,
    "new_plan_deviation_frac": 0.0
  },
  {
    "family": "scan",
    "method": "isomer",
    "n": 28,
    "row_qerr_gm": 2.0443585692852837,
    "qerr_improvement_pct": 94.32799267743299,
    "beats_stale_qerr_frac": 0.9642857142857143,
    "fresh_plan_match_frac": 1.0,
    "fresh_root_match_frac": 1.0,
    "fresh_scan_match_frac": 1.0,
    "fresh_join_match_frac": 1.0,
    "stale_fresh_changed_queries": 7,
    "plan_recovery_frac": 1.0,
    "new_plan_deviation_frac": 0.0
  },
  {
    "family": "scan",
    "method": "oasis",
    "n": 28,
    "row_qerr_gm": 3.0201004131676985,
    "qerr_improvement_pct": 91.62082820707742,
    "beats_stale_qerr_frac": 0.9285714285714286,
    "fresh_plan_match_frac": 0.9642857142857143,
    "fresh_root_match_frac": 0.9642857142857143,
    "fresh_scan_match_frac": 0.9642857142857143,
    "fresh_join_match_frac": 1.0,
    "stale_fresh_changed_queries": 7,
    "plan_recovery_frac": 1.0,
    "new_plan_deviation_frac": 0.047619047619047616
  },
  {
    "family": "scan",
    "method": "oasis_projected",
    "n": 28,
    "row_qerr_gm": 2.1006922258340754,
    "qerr_improvement_pct": 94.17169675300356,
    "beats_stale_qerr_frac": 0.9642857142857143,
    "fresh_plan_match_frac": 1.0,
    "fresh_root_match_frac": 1.0,
    "fresh_scan_match_frac": 1.0,
    "fresh_join_match_frac": 1.0,
    "stale_fresh_changed_queries": 7,
    "plan_recovery_frac": 1.0,
    "new_plan_deviation_frac": 0.0
  },
  {
    "family": "scan",
    "method": "hybrid",
    "n": 28,
    "row_qerr_gm": 2.0829616332240826,
    "qerr_improvement_pct": 94.22088971388051,
    "beats_stale_qerr_frac": 0.9642857142857143,
    "fresh_plan_match_frac": 1.0,
    "fresh_root_match_frac": 1.0,
    "fresh_scan_match_frac": 1.0,
    "fresh_join_match_frac": 1.0,
    "stale_fresh_changed_queries": 7,
    "plan_recovery_frac": 1.0,
    "new_plan_deviation_frac": 0.0
  },
  {
    "family": "scan",
    "method": "aggressive_hybrid",
    "n": 28,
    "row_qerr_gm": 2.0947964517905464,
    "qerr_improvement_pct": 94.18805438910982,
    "beats_stale_qerr_frac": 0.9642857142857143,
    "fresh_plan_match_frac": 1.0,
    "fresh_root_match_frac": 1.0,
    "fresh_scan_match_frac": 1.0,
    "fresh_join_match_frac": 1.0,
    "stale_fresh_changed_queries": 7,
    "plan_recovery_frac": 1.0,
    "new_plan_deviation_frac": 0.0
  },
  {
    "family": "scan",
    "method": "fresh",
    "n": 28,
    "row_qerr_gm": 1.3681056773921882,
    "qerr_improvement_pct": 96.20423465002675,
    "beats_stale_qerr_frac": 1.0,
    "fresh_plan_match_frac": 1.0,
    "fresh_root_match_frac": 1.0,
    "fresh_scan_match_frac": 1.0,
    "fresh_join_match_frac": 1.0,
    "stale_fresh_changed_queries": 7,
    "plan_recovery_frac": 1.0,
    "new_plan_deviation_frac": 0.0
  },
  {
    "family": "join",
    "method": "stale",
    "n": 28,
    "row_qerr_gm": 36.042946579978334,
    "qerr_improvement_pct": 0.0,
    "beats_stale_qerr_frac": 0.0,
    "fresh_plan_match_frac": 0.21428571428571427,
    "fresh_root_match_frac": 0.4642857142857143,
    "fresh_scan_match_frac": 0.21428571428571427,
    "fresh_join_match_frac": 0.4642857142857143,
    "stale_fresh_changed_queries": 22,
    "plan_recovery_frac": 0.0,
    "new_plan_deviation_frac": 0.0
  },
  {
    "family": "join",
    "method": "isomer",
    "n": 28,
    "row_qerr_gm": 2.0443585692852837,
    "qerr_improvement_pct": 94.32799267743299,
    "beats_stale_qerr_frac": 0.9642857142857143,
    "fresh_plan_match_frac": 0.9642857142857143,
    "fresh_root_match_frac": 0.9642857142857143,
    "fresh_scan_match_frac": 0.9642857142857143,
    "fresh_join_match_frac": 0.9642857142857143,
    "stale_fresh_changed_queries": 22,
    "plan_recovery_frac": 0.9545454545454546,
    "new_plan_deviation_frac": 0.0
  },
  {
    "family": "join",
    "method": "oasis",
    "n": 28,
    "row_qerr_gm": 3.0201004131676985,
    "qerr_improvement_pct": 91.62082820707742,
    "beats_stale_qerr_frac": 0.9285714285714286,
    "fresh_plan_match_frac": 0.8928571428571429,
    "fresh_root_match_frac": 0.9285714285714286,
    "fresh_scan_match_frac": 0.8928571428571429,
    "fresh_join_match_frac": 0.9285714285714286,
    "stale_fresh_changed_queries": 22,
    "plan_recovery_frac": 0.9090909090909091,
    "new_plan_deviation_frac": 0.16666666666666666
  },
  {
    "family": "join",
    "method": "oasis_projected",
    "n": 28,
    "row_qerr_gm": 2.1006922258340754,
    "qerr_improvement_pct": 94.17169675300356,
    "beats_stale_qerr_frac": 0.9642857142857143,
    "fresh_plan_match_frac": 0.9642857142857143,
    "fresh_root_match_frac": 0.9642857142857143,
    "fresh_scan_match_frac": 0.9642857142857143,
    "fresh_join_match_frac": 0.9642857142857143,
    "stale_fresh_changed_queries": 22,
    "plan_recovery_frac": 0.9545454545454546,
    "new_plan_deviation_frac": 0.0
  },
  {
    "family": "join",
    "method": "hybrid",
    "n": 28,
    "row_qerr_gm": 2.0829616332240826,
    "qerr_improvement_pct": 94.22088971388051,
    "beats_stale_qerr_frac": 0.9642857142857143,
    "fresh_plan_match_frac": 0.9642857142857143,
    "fresh_root_match_frac": 0.9642857142857143,
    "fresh_scan_match_frac": 0.9642857142857143,
    "fresh_join_match_frac": 0.9642857142857143,
    "stale_fresh_changed_queries": 22,
    "plan_recovery_frac": 0.9545454545454546,
    "new_plan_deviation_frac": 0.0
  },
  {
    "family": "join",
    "method": "aggressive_hybrid",
    "n": 28,
    "row_qerr_gm": 2.0947964517905464,
    "qerr_improvement_pct": 94.18805438910982,
    "beats_stale_qerr_frac": 0.9642857142857143,
    "fresh_plan_match_frac": 0.9642857142857143,
    "fresh_root_match_frac": 0.9642857142857143,
    "fresh_scan_match_frac": 0.9642857142857143,
    "fresh_join_match_frac": 0.9642857142857143,
    "stale_fresh_changed_queries": 22,
    "plan_recovery_frac": 0.9545454545454546,
    "new_plan_deviation_frac": 0.0
  },
  {
    "family": "join",
    "method": "fresh",
    "n": 28,
    "row_qerr_gm": 1.3681056773921882,
    "qerr_improvement_pct": 96.20423465002675,
    "beats_stale_qerr_frac": 1.0,
    "fresh_plan_match_frac": 1.0,
    "fresh_root_match_frac": 1.0,
    "fresh_scan_match_frac": 1.0,
    "fresh_join_match_frac": 1.0,
    "stale_fresh_changed_queries": 22,
    "plan_recovery_frac": 1.0,
    "new_plan_deviation_frac": 0.0
  },
  {
    "family": "join_dim_filter",
    "method": "stale",
    "n": 28,
    "row_qerr_gm": 33.704639478730286,
    "qerr_improvement_pct": 0.0,
    "beats_stale_qerr_frac": 0.0,
    "fresh_plan_match_frac": 0.5357142857142857,
    "fresh_root_match_frac": 0.5357142857142857,
    "fresh_scan_match_frac": 0.5357142857142857,
    "fresh_join_match_frac": 0.5357142857142857,
    "stale_fresh_changed_queries": 13,
    "plan_recovery_frac": 0.0,
    "new_plan_deviation_frac": 0.0
  },
  {
    "family": "join_dim_filter",
    "method": "isomer",
    "n": 28,
    "row_qerr_gm": 1.8317782645155634,
    "qerr_improvement_pct": 94.56520439664834,
    "beats_stale_qerr_frac": 1.0,
    "fresh_plan_match_frac": 0.9642857142857143,
    "fresh_root_match_frac": 0.9642857142857143,
    "fresh_scan_match_frac": 0.9642857142857143,
    "fresh_join_match_frac": 0.9642857142857143,
    "stale_fresh_changed_queries": 13,
    "plan_recovery_frac": 0.9230769230769231,
    "new_plan_deviation_frac": 0.0
  },
  {
    "family": "join_dim_filter",
    "method": "oasis",
    "n": 28,
    "row_qerr_gm": 2.8128664470196676,
    "qerr_improvement_pct": 91.65436423435189,
    "beats_stale_qerr_frac": 0.9285714285714286,
    "fresh_plan_match_frac": 0.8928571428571429,
    "fresh_root_match_frac": 0.8928571428571429,
    "fresh_scan_match_frac": 0.8928571428571429,
    "fresh_join_match_frac": 0.8928571428571429,
    "stale_fresh_changed_queries": 13,
    "plan_recovery_frac": 1.0,
    "new_plan_deviation_frac": 0.2
  },
  {
    "family": "join_dim_filter",
    "method": "oasis_projected",
    "n": 28,
    "row_qerr_gm": 1.885380184010402,
    "qerr_improvement_pct": 94.40617014995757,
    "beats_stale_qerr_frac": 1.0,
    "fresh_plan_match_frac": 0.9642857142857143,
    "fresh_root_match_frac": 0.9642857142857143,
    "fresh_scan_match_frac": 0.9642857142857143,
    "fresh_join_match_frac": 0.9642857142857143,
    "stale_fresh_changed_queries": 13,
    "plan_recovery_frac": 0.9230769230769231,
    "new_plan_deviation_frac": 0.0
  },
  {
    "family": "join_dim_filter",
    "method": "hybrid",
    "n": 28,
    "row_qerr_gm": 1.8695499278817649,
    "qerr_improvement_pct": 94.45313773772432,
    "beats_stale_qerr_frac": 1.0,
    "fresh_plan_match_frac": 0.9642857142857143,
    "fresh_root_match_frac": 0.9642857142857143,
    "fresh_scan_match_frac": 0.9642857142857143,
    "fresh_join_match_frac": 0.9642857142857143,
    "stale_fresh_changed_queries": 13,
    "plan_recovery_frac": 0.9230769230769231,
    "new_plan_deviation_frac": 0.0
  },
  {
    "family": "join_dim_filter",
    "method": "aggressive_hybrid",
    "n": 28,
    "row_qerr_gm": 1.8799077712740746,
    "qerr_improvement_pct": 94.42240652815642,
    "beats_stale_qerr_frac": 1.0,
    "fresh_plan_match_frac": 0.9642857142857143,
    "fresh_root_match_frac": 0.9642857142857143,
    "fresh_scan_match_frac": 0.9642857142857143,
    "fresh_join_match_frac": 0.9642857142857143,
    "stale_fresh_changed_queries": 13,
    "plan_recovery_frac": 0.9230769230769231,
    "new_plan_deviation_frac": 0.0
  },
  {
    "family": "join_dim_filter",
    "method": "fresh",
    "n": 28,
    "row_qerr_gm": 1.2674077639572676,
    "qerr_improvement_pct": 96.23966378647344,
    "beats_stale_qerr_frac": 1.0,
    "fresh_plan_match_frac": 1.0,
    "fresh_root_match_frac": 1.0,
    "fresh_scan_match_frac": 1.0,
    "fresh_join_match_frac": 1.0,
    "stale_fresh_changed_queries": 13,
    "plan_recovery_frac": 1.0,
    "new_plan_deviation_frac": 0.0
  }
]